organize/__init__.py
organize/__main__.py
organize/__version__.py
organize/action.py
organize/actions/__init__.py
organize/actions/common/__init__.py
organize/actions/common/conflict.py
organize/actions/common/target_path.py
organize/actions/confirm.py
organize/actions/copy.py
organize/actions/delete.py
organize/actions/echo.py
organize/actions/hardlink.py
organize/actions/macos_tags.py
organize/actions/move.py
organize/actions/python.py
organize/actions/rename.py
organize/actions/shell.py
organize/actions/symlink.py
organize/actions/trash.py
organize/actions/write.py
organize/cli.py
organize/config.py
organize/errors.py
organize/filter.py
organize/filters/__init__.py
organize/filters/common/__init__.py
organize/filters/common/timefilter.py
organize/filters/created.py
organize/filters/date_added.py
organize/filters/date_lastused.py
organize/filters/duplicate.py
organize/filters/empty.py
organize/filters/exif.py
organize/filters/extension.py
organize/filters/filecontent.py
organize/filters/hash.py
organize/filters/lastmodified.py
organize/filters/macos_tags.py
organize/filters/mimetype.py
organize/filters/name.py
organize/filters/python.py
organize/filters/regex.py
organize/filters/size.py
organize/find_config.py
organize/location.py
organize/logger.py
organize/output/__init__.py
organize/output/_sender.py
organize/output/default.py
organize/output/jsonl.py
organize/output/output.py
organize/output/saving.py
organize/py.typed
organize/registry.py
organize/resource.py
organize/rule.py
organize/template.py
organize/utils.py
organize/validators.py
organize/walker.py
organize_tool-3.2.5.dist-info/LICENSE.txt
organize_tool-3.2.5.dist-info/METADATA
organize_tool-3.2.5.dist-info/WHEEL
organize_tool-3.2.5.dist-info/entry_points.txt
organize_tool-3.2.5.dist-info/RECORD
