Metadata-Version: 2.1
Name: organize-tool
Version: 3.2.5
Summary: The file management automation tool
Home-page: https://github.com/tfeldmann/organize
License: MIT
Keywords: file,management,automation,tool,organization,rules,yaml
Author: Thomas Feldmann
Author-email: mail@tfeldmann.de
Requires-Python: >=3.9,<4.0
Classifier: Development Status :: 5 - Production/Stable
Classifier: Environment :: Console
Classifier: Intended Audience :: End Users/Desktop
Classifier: License :: OSI Approved :: MIT License
Classifier: Natural Language :: English
Classifier: Operating System :: OS Independent
Classifier: Programming Language :: Python :: 3
Classifier: Programming Language :: Python :: 3.9
Classifier: Programming Language :: Python :: 3.10
Classifier: Programming Language :: Python :: 3.11
Classifier: Programming Language :: Python :: 3.12
Classifier: Topic :: Utilities
Provides-Extra: docs
Requires-Dist: ExifRead (==2.3.2)
Requires-Dist: Jinja2 (>=3.1.2,<4.0.0)
Requires-Dist: PyYAML (>=6.0,<7.0)
Requires-Dist: Send2Trash[nativelib] (>=1.8.2,<2.0.0)
Requires-Dist: arrow (>=1.3.0,<2.0.0)
Requires-Dist: docopt-ng (>=0.9.0,<0.10.0)
Requires-Dist: docx2txt (>=0.8,<0.9)
Requires-Dist: macos-tags (>=1.5.1,<2.0.0) ; sys_platform == "darwin"
Requires-Dist: markupsafe (==2.0.1) ; extra == "docs"
Requires-Dist: mkdocs (>=1.5.3,<2.0.0) ; extra == "docs"
Requires-Dist: mkdocs-autorefs (>=0.5.0,<0.6.0) ; extra == "docs"
Requires-Dist: mkdocs-include-markdown-plugin (>=6.0.4,<7.0.0) ; extra == "docs"
Requires-Dist: mkdocstrings[python] (>=0.24.0,<0.25.0) ; extra == "docs"
Requires-Dist: natsort (>=8.4.0,<9.0.0)
Requires-Dist: pdfminer-six (>=20231228,<20231229)
Requires-Dist: platformdirs (>=4.0.0,<5.0.0)
Requires-Dist: pydantic (>=2.3.0,<3.0.0)
Requires-Dist: rich (>=13.4.2,<14.0.0)
Requires-Dist: simplematch (>=1.4,<2.0)
Project-URL: Documentation, https://organize.readthedocs.io
Project-URL: Repository, https://github.com/tfeldmann/organize
